odoo/addons/loyalty_incompatibility/README.rst
odoo/addons/loyalty_incompatibility/__init__.py
odoo/addons/loyalty_incompatibility/__manifest__.py
odoo/addons/loyalty_incompatibility/i18n/es.po
odoo/addons/loyalty_incompatibility/i18n/it.po
odoo/addons/loyalty_incompatibility/i18n/loyalty_incompatibility.pot
odoo/addons/loyalty_incompatibility/models/__init__.py
odoo/addons/loyalty_incompatibility/models/loyalty_program.py
odoo/addons/loyalty_incompatibility/readme/CONFIGURE.md
odoo/addons/loyalty_incompatibility/readme/CONTRIBUTORS.md
odoo/addons/loyalty_incompatibility/readme/DESCRIPTION.md
odoo/addons/loyalty_incompatibility/static/description/icon.png
odoo/addons/loyalty_incompatibility/static/description/index.html
odoo/addons/loyalty_incompatibility/tests/__init__.py
odoo/addons/loyalty_incompatibility/tests/test_loyalty_incompatibility.py
odoo/addons/loyalty_incompatibility/views/loyalty_program_views.xml
odoo_addon_loyalty_incompatibility-18.0.1.0.0.2.dist-info/METADATA
odoo_addon_loyalty_incompatibility-18.0.1.0.0.2.dist-info/WHEEL
odoo_addon_loyalty_incompatibility-18.0.1.0.0.2.dist-info/top_level.txt
odoo_addon_loyalty_incompatibility-18.0.1.0.0.2.dist-info/RECORD
